Workbook
Name Indicatore_on_off: Governo!$C$65

Sheet PdR 5-2013
C7: I campi di colore verde sono gli unici compilabili. Per maggiori informazioni per la corretta compilazione fare riferimento alla Prassi di Riferimento UNI/PdR 5:2013
C12: Comune di
C16: compilazione a cura di
C18: settore di appartenenza
C20: recapito mail
C22: recapito telefonico

Sheet Governo
A1: PROCESSI DI GOVERNO
C3: Indicatore G.1 | D3: Autonomia Finanziaria
C4: Evidenzia in quale quota l'amministrazione locale faccia leva sul prelievo tributario (imposte, tasse ed altri tributi, e sulle entrate extratributarie (proventi dei servizi pubblici locale, proventi patrimoniali, utili di aziende partecipate o controllate) per procurari le entrate di parte corrente
C6: entrate tributarie (TitoloI) | D6: entrate extratributarie (Titolo II+III) | E6: Totale entrate | F6: G.1
C7: 8683561.4 | D7: 4180143.2 | E7: 15909375 | F7: =(C7+D7)/E7 -> 0.80856126
C9: Note:
C13: Indicatore G.2 | D13: Velocotà di riscossione annua
C14: Indica l'efficienza di un'amministrazione locale, indica la sua capacità di realizzare i crediti nell'anno di Competenza
C16: Riscossioni Titolo I | D16: Riscossioni Titolo III | E16: Accertamenti Titolo I | F16: Accertamenti Titolo III | G16: G.2
C17: 90 | D17: 90 | E17: 100 | F17: 100 | G17: =(C17+D17)/(E17+F17) -> 0.9
C19: Note:
C24: Indicatore G.3 | D24: Efficacia di gestione del Bilancio
C25: Evidenzia la capacità di previsione dell'amministrazione locale misurando lo scostamento tra quanto pianificato e quanto rendicontato alla fine del periodo di riferimento.
C27: Bilancio di Previsione | D27: Rendiconto | E27: G.3
A28: ENTRATE | B28: Tit. I | C28: 100 | D28: 90 | E28: =IF(C28=D28,"=1",IF(C28<D28,"<1",">1")) -> >1
B29: Tit. II | C29: 10 | D29: 11 | E29: =IF(C29=D29,"=1",IF(C29<D29,"<1",">1")) -> <1
B30: Tit. III | C30: 11 | D30: 9 | E30: =IF(C30=D30,"=1",IF(C30<D30,"<1",">1")) -> >1
B31: Tit. IV | C31: 8 | D31: 8 | E31: =IF(C31=D31,"=1",IF(C31<D31,"<1",">1")) -> =1
B32: Tit. V | C32: 12 | D32: 10 | E32: =IF(C32=D32,"=1",IF(C32<D32,"<1",">1")) -> >1
A33: SPESA | B33: Tit. I | C33: 12 | D33: 14 | E33: =IF(C33=D33,"=1",IF(C33<D33,"<1",">1")) -> <1
B34: Tit. II | C34: 3 | D34: 3 | E34: =IF(C34=D34,"=1",IF(C34<D34,"<1",">1")) -> =1
B35: Tit. III | C35: 5 | D35: 1 | E35: =IF(C35=D35,"=1",IF(C35<D35,"<1",">1")) -> >1
C37: Note:
C41: Indicatore G.4 | D41: Propensione all'investimento
C42: Indica la propensione dell'amministrazione locale ad investire in fattori pluriennali soggetti ad ammortamento (dalla realizzazione di infrastrutture alla acquisizione di beni).
C44: Spese in conto capitale | D44: numero abitanti | E44: G.4
C45: 1960000 | D45: 15520 | E45: =C45/D45 -> 126.28866
C47: Note:
C51: Indicatore G.5 | D51: Pressione tributaria per abitante
C52: Indica il benessere dell'amministrazione locale, in quanto permette di valutare il peso medio fiscale che i cittadini devono sopportare per permettere che l'amministrazione locale faccia fronte alle proprie spese di gestione.
C54: Entrate tributarie | D54: numero abitanti | E54: G.5
C55: =C7 -> 8683561.4 | D55: =D45 -> 15520 | E55: =C55/D55 -> 559.50782
C57: Note:
C61: Indicatore G.6 | D61: Rispetto del patto di stabilità
C62: Indica se l'amministrazione locale è in grado di tenere sotto controllo l'indebitamento netto definito come il saldo fra entrate e spese finali, al netto delle operazioni finanziarie (riscossione e concessioni crediti, partecipazioni e conferimenti, anticipazioni).
C64: Indicatore on/off
C65: SI
C67: Note:
C71: Indicatore G.7 | D71: Capacità di ascolto dei cittadini/utenti
C72: Permette di trasformare in valutazione quantitativa il parere soggettivo dei cittadini riguardo alla capacità della propria amministrazione locale di ascoltare le loro esigenze.
C74: Risposta che ha ricevuto il maggior numero di "voti" | E74: G.7
C75: 5 | E75: =C75 -> 5
C77: Note:
C78: E' il valore raccolto inserendo nel questionario di CS una domanda del tipo "dare un valutazione della capacità di ascolto delle esigenze dei cittadini da parte della propria amministrazione locale". L'unità di misura dipende dalla scala che è stata adottata per la formulazione delle risposte alle domande del questionario.
C81: Indicatore G.8 | D81: Orientamento all'innovazione
C82: Permette di valutare quale sia la propensione dell'amministrazione locale ad innovare attraverso la frequenza con la quale intraprende progetti innovativi, ossia .attività aventi come obiettivo quello di realizzare un servizio e/o adottare un modello organizzativo non richiesti per legge, ma finalizzati ad incrementare il benessere della collettività o di una delle sue componenti (cittadini, commercianti, imprenditori, ecc.), sia in termini di ottimizzazione delle risorse che di soddisfazione di bisogni latenti
C84: n.ro progetti innovativi nel triennio | D84: G.8
C85: 2 | D85: =C85/3 -> 0.66666667
C87: Note:
C88: Periodo di riferimento 3 anni
C91: Indicatore G.9 | D91: Orientamento alla gestione per processi
C92: Permette di capire quanto è diffuso il concetto di processo e di monitoraggio dei processi all'interno dell'amministrazione locale.
C94: Numero processi monitorati | D94: numero totale dei processi | E94: G.9
C95: 5 | D95: 10 | E95: =C95/D95 -> 0.5
C97: Note:
C101: Indicatore G.10 | D101: Stabilità del fondo cassa
C102: Avere un fondo cassa stabile garantisce un certo equilibrio, una certa costanza tra incassi e pagamenti che è indice di salute del bilancio dell' amministrazione locale
C104: Fondo cassa al 31.12 | D104: Fondo cassa al 31.12 dell'anno precedente | E104: G.10
C105: 5296750.5 | D105: 5611961.1 | E105: =IF(C106=D106,"=1",IF(C106<D106,"<1",">1")) -> <1
C106: =ROUND(C105,-5) -> 5300000 | D106: =ROUND(D105,-5) -> 5600000
C107: Note:
C108: La formula lavora arrotondando i valori ai € 100.000
C111: Indicatore G.11 | D111: Coefficiente di spesa per OOPP sulle risorse
C112: Misura la capacità dell'amministrazione locale di rispettare i propri piani economico- finanziari. Misura quanto tra le risorse (disponibilità finanziarie) attribuite ad ogni responsabile di spesa, viene destinato a spese per investimenti.E' indicatore di efficacia
C114: Spesa prevista per OOPP | D114: Totale risorse affidate | E114: G.11
C115: 50 | D115: 200 | E115: =C115/D115 -> 0.25
C117: Note:

Sheet Operativi
A1: PROCESSI OPERATIVI
C3: Indicatore O.1 | D3: Rispetto dei tempi di rilascio dei documenti
C4: Misura l'efficacia del processo di rilascio dei documenti valutando il rispetto dei tempi di rilascio previsti. Effettua la misurazione con riferimento ad alcune tipologie di documenti rappresentative dell'insieme. La formula misura la media dell'indicatore "tempo rilascio eff.(te)/tempo rilascio previsto (tp)" calcolato per un panel di documenti "tipo", cioè : carta d'identità, certificati urbanistici, autorizzazione occupazione suolo pubblico, permesso di sosta per disabili.
C6: ∑ tempi effettivi di rilascio | D6: tempo previsto | E6: numero documenti emessi | F6: parziali | G6: O.1
A7: CI | C7: 24 | D7: 2 | E7: 10 | F7: =(C7+D7)/E7 -> 2.6 | G7: =(F7+F8+F9+F10)/4 -> 11.5
A8: CDU | C8: 200 | D8: 30 | E8: 10 | F8: =(C8+D8)/E8 -> 23
A9: AOSP | C9: 140 | D9: 15 | E9: 10 | F9: =(C9+D9)/E9 -> 15.5
A10: PD | C10: 19 | D10: 30 | E10: 10 | F10: =(C10+D10)/E10 -> 4.9
C12: Note:
C13: Periodo di riferimento: 3 mesi. C.I =Carte d'identità; CDU= Certificati di destinazione urbanistica; AOSP= Autorizzazioni occupazione suolo pubblico; PD=Permessi per disabili
C16: Indicatore O.2 | D16: Rispetto dei tempi di alcune pratiche tipo
C17: Misura la capacità dell'amministrazione locale di rispettare itempi di trattamento previsti. È indicatore di efficacia
C19: Media tempi effettivi di rilascio | D19: tempo previsto | E19: numero documenti emessi | F19: parziali | G19: O.2
A20: CR | C20: 2 | D20: 2 | E20: 10 | F20: =(C20+D20)/E20 -> 0.4 | G20: =(F20+F21+F22)/3 -> 3.6666667
A21: DIAP | C21: 28 | D21: 30 | E21: 10 | F21: =(C21+D21)/E21 -> 5.8
A22: SCIA | C22: 18 | D22: 30 | E22: 10 | F22: =(C22+D22)/E22 -> 4.8
C24: Note:
C25: Periodo di riferimento: 3 mesi. CR=Cambi di residenza; DIAP= Denuncia di inizio attività; SCIA= Segnalazione Certificata Inizio Attività
C28: Indicatore O.3 | D28: Accessibilità ai servizi
C29: Serve a valutare la disponibilità dell'amministrazione locale a mantenere accessibili al pubblico, in termini di orari di apertura, i servizi dotati di sportello.
C31: ∑ delle ore di apertura settimanali di tutti gli sportelli | D31: numero degli sportelli | E31: O.3
C32: =(5+5+10) -> 20 | D32: 3 | E32: =(C32/36)/D32 -> 0.18518519
C34: Note:
C35: Si riferisce al momento in cui viene fatta la misurazione
C38: Indicatore O.4 | D38: Assenza di barriere architettoniche
C39: Misura il livello di adeguamento dell'amministrazione locale ad un requisito previsto dalla legge.
C41: numero edifici attrezzati | D41: numero totale edifici | E41: O.4
C42: 4 | D42: 5 | E42: =C42/D42 -> 0.8
C44: Note:
C45: Si riferisce all'anno. I dati possono essere reperiti nel PEBA (Piano eliminazione barriere architettoniche)
C48: Indicatore O.5 | D48: Tempo medio di attesa allo sportello
C49: Misura l'efficacia del processo di erogazione dei servizi tramite sportello. Valuta la capacità dell'amministrazione locale di rispondere con tempestività alle richieste.
C51: ∑ tempi medi di attesa di ciascun sportello | D51: numero degli sportelli | E51: O.5
C52: =(5+10+30+5+20+2+8+15+5) -> 100 | D52: =D32 -> 3 | E52: =C52/D52 -> 33.333333
C54: Note:
C55: E' espresso in minuti. Si riferisce ad una misurazione effettuata 1 settimana al mese, per almeno 3 mesi consecutivi
C58: Indicatore O.6 | D58: Livello generale di soddisfazione dei cittadini
C59: Misura l'efficacia complessiva della macchina dell'amministrazione locale
C61: Risposta che ha ricevuto il maggior numero di "voti" opp. Media del livello di soddisfazione riferito ai singoli servizi | E61: O.6
C62: 4 | E62: =C62 -> 4
C64: Note:
C65: L'unità di misura dipende dalla scala che è stata adottata per la formulazione delle risposte
C68: Indicatore O.7 | D68: Rispetto dei tempi di realizzazione delle OO.PP
C69: Misura la capacità dell'amministrazione locale di rispettare i propri piani. È indicatore di efficacia.
C71: ∑ dell'indicatore ottenuto per ogni OP = tempo di realizzazione effettivo / tempo di realizzazione previsto | E71: numero totale di OOPP realizzate | F71: O.7
C72: 2.7 | E72: 3 | F72: =C72/E72 -> 0.9
C74: Note:
C75: Periodo di riferimento: un anno. Rapporto tra tempi da cui si ricava un valore assoluto.
C78: Indicatore O.8 | D78: Tempo medio di intervento su segnalazioni per manutenzione ordinaria alle infrastrutture
C79: Misura l'efficacia del processo di gestione delle richieste interventi di manutenzione attraverso una valutazione della tempestività di risposta
C81: ∑ dell'indicatore ottenuto per ogni intervento di manutenzione = data intervento - data ricezione segnalazione | E81: numero totale interventi | F81: O.8
C82: =2+4+3 -> 9 | E82: 3 | F82: =C82/E82 -> 3
C84: Note:
C85: Periodo di riferimento: un anno. L'indicatore ottenuto per ogni intervento di manutenzione è misurato in giorni
C88: Indicatore O.9 | D88: Capacità di conservazione del patrimonio e del verde pubblico
C89: Misura la capacità dell'amministrazione locale di rispettare i propri piani. È indicatore di efficacia.
C91: N.ro interventi di manutenzione ord. e straord. effettuati | D91: N.ro interventi di manutenzione ord. e straord. programmati | E91: O.9
C92: 9 | D92: 10 | E92: =C92/D92 -> 0.9
C94: Note:
C95: Periodo di riferimento: un anno.
C98: Indicatore O.10 | D98: Disponibilità dei servizi sociali
C99: Misura la capacità dell'amministrazione locale di soddisfare la domanda dei seguenti servizi sociali: edilizia popolare, assistenza domiciliare, sostegno minori, contributi economici per persone in difficoltà, portatori di handicap.
C101: N.ro domande soddisfatte | D101: N.ro domande accolte | E101: O.10
C102: 30 | D102: 32 | E102: =C102/D102 -> 0.9375
C104: Note:
C105: Periodo di riferimento: un anno.
C108: Indicatore O.11 | D108: Disponibilità dei servizi culturali / per il tempo libero
C109: Misura la capacità dell'amministrazione locale di soddisfare la domanda dei seguenti servizi culturali/per il tempo libero: partecipazione a corsi/attività, utilizzo strutture sportive/culturali. L'indicatore non è applicabile alle biblioteche.
C111: N.ro domande soddisfatte | D111: N.ro domande accolte | E111: O.11
C112: 87 | D112: 87 | E112: =C112/D112 -> 1
C114: Note:
C115: Periodo di riferimento: un anno.
C118: Indicatore O.12 | D118: Efficacia servizi educativi
C119: Misura la capacità dell'amministrazione locale di offrire ai cittadini servizi educativi in linea con le loro esigenze, tramite domanda da inserire nel questionario di customer satisfaction
C121: Risposta che ha ricevuto il maggior numero di "voti" opp. Media del livello di soddisfazione riferito ai singoli servizi | E121: O.12
C122: 3 | E122: =C122 -> 3
C124: Note:
C125: Inserire nel questionario domande del tipo "come valuta l'efficacia dei servizi educativi di cui ha usufruito?" ed elaborare statisticamente le relative risposte. L'unità di misura dipende dalla scala che è stata adottata per la formulazione delle risposte
C128: Indicatore O.13 | D128: Soddisfazione richieste servizi scolastici
C129: Misura la capacità dell'amministrazione locale di soddisfare la domanda dei seguenti servizi scolastici: trasporto, mensa, pre-scuola, asili nido.
C131: N.ro domande soddisfatte | D131: N.ro domande presentate | E131: O.13
C132: 1100 | D132: 1145 | E132: =C132/D132 -> 0.96069869
C134: Note:
C135: Periodo di riferimento: un anno.
C138: Indicatore O.14 | D138: Sicurezza dei cittadini - Reati contro il patrimonio
C139: Misura l'incidenza dei reati contro il patrimonio all'interno dell'amministrazione locale.
C141: N.ro denunce per reati contro il patrimonio presentate | D141: N.ro abitanti | E141: O.14
C142: 4 | D142: =Governo!D45 -> 15520 | E142: =C142/D142 -> 0.00025773196
C144: Note:
C145: Numero medio riferito all'anno
C148: Indicatore O.15 | D148: Sicurezza dei cittadini - Reati contro le persone
C149: Misura l'incidenza dei reati contro le persone all'interno dell'amministrazione locale.
C151: N.ro denunce per reati contro le persone presentate | D151: N.ro abitanti | E151: O.15
C152: 4 | D152: =Governo!D45 -> 15520 | E152: =C152/D152 -> 0.00025773196
C154: Note:
C155: Numero medio riferito all'anno
C158: Indicatore O.16 | D158: Sicurezza dei cittadini - Disponibilità agenti sul territorio
C159: Misura l'impiego di risorse (in termini di uomini) da parte dell'amministrazione locale per garantire la sicurezza dei cittadini.
C161: N.ro agenti | D161: N.ro abitanti | E161: O.16
C162: 8 | D162: =Governo!D45 -> 15520 | E162: =(C162/D162)*1000 -> 0.51546392
...

Sheet Supporto
A1: PROCESSI DI SUPPORTO
C3: Indicatore S.1 | D3: Tempo medio formazione atti interni (delibere, determine)
C4: Misura l'efficienza del processo di gestione degli atti interni con un focus sulle due tipologie di atti più rilevanti. Interessante è non soltanto il tempo medio necessario per la formazione dei due atti, ma anche il range (t.max-t.min) all'interno del quale si oscilla.
C6: ∑ tempi di formazione di ciascuna delibera | D6: numero di delibere | E6: ∑ tempi di formazione di ciascuna determina | F6: numero di determine | G6: S.1
C7: =(4*81)+(6*22) -> 456 | D7: =81+22 -> 103 | E7: =7*187 -> 1309 | F7: 187 | G7: =(C7/D7)+(E7/F7) -> 11.427184
C9: Note:
C10: Periodo di riferimento: 3 mesi. Tempo misurato in giorni. Il tempo è calcolato dal momento di inizio (bozza) alla formalizzazione dell'atto (pubblicazione), comprensivo delle eventuali interruzioni.
C13: Indicatore S.2 | D13: Rispetto tempi di emissione atti interni (delibere, determina)
C14: Misura l'efficacia del processo di gestione degli atti interni con un focus sulle due tipologie di atti più rilevanti.
C16: ∑ tempi rilascio effettivo di ogni delibera | D16: tempo di rilascio previsto per le delibere | E16: Numero di delibere | F16: S.2
C17: 456 | D17: 8 | E17: 103 | F17: =((C17/D17)/E17)+((C19/D19)/E19) -> 1.5533981
C18: ∑ tempi rilascio effettivo di ogni determina | D18: tempo di rilascio previsto per le determine | E18: Numero di determine
C19: 14 | D19: 7 | E19: 2
C21: Note:
C22: Periodo di riferimento: 3 mesi. Tempo misurato in giorni. Rapporto tra tempi da cui si ricava un valore assoluto
C25: Indicatore S.3 | D25: Funzionamento del protocollo in entrata
C26: Misura l'efficienza del processo di smistamento della posta in entrata, misurando il tempo medio di consegna agli uffici della posta proveniente dall'esterno
C28: ∑ tempo medio (gg) di consegna per ogni documento (data arrivo protocollo - data consegna ufficio) | D28: Numero documenti in entrata | E28: S.3
C29: 19987 | D29: 20951 | E29: =C29/D29 -> 0.95398788
C31: Note:
C32: Periodo di riferimento: 3 mesi. Tempo medio misurato in giorni.
C35: Indicatore S.4 | D35: Funzionamento del protocollo in uscita
C36: Misura l'efficienza del processo di spedizione della posta in uscita, misurando il tempo medio di spedizione della posta diretta all'esterno
C38: ∑ tempo medio (gg) di spedizione per ogni documento (data partenza dal protocollo - data documento) | D38: Numero documenti in uscita | E38: S.4
C39: 11187 | D39: 13967 | E39: =C39/D39 -> 0.8009594
C41: Note:
C42: Periodo di riferimento: 3 mesi. Tempo medio misurato in giorni.
C45: Indicatore S.5 | D45: Grado di dematerializzazione degli atti
C46: Misura l'impegno dell'amministrazione locale a procedere verso la completa sostituzione del proprio archivio cartaceo con un archivio informatico che permetta ai cittadini ed alle imprese di consultare gli atti amministrativi e conoscere lo stato di avanzamento dei propri procedimenti per via telematica.
C48: N.ro atti (delibere + determine + contratti) dematerializzati) | D48: Totale atti (delibere + determine + contratti) dematerializzati) | E48: S.5
C49: 20 | D49: =(456+1309+50) -> 1815 | E49: =C49/D49 -> 0.011019284
C51: Note:
C52: Periodo di riferimento: un anno.
C55: Indicatore S.6 | D55: Copertura dei servizi da parte di sistemi di monitoraggio della customer satisfaction
C56: Misura l'attenzione dell'amministrazione locale nei confronti della soddisfazione dei cittadini e la sua volontà di misurarsi per individuare punti di forza e aree da migliorare.
C58: Numero servizi coperti dalla CS | D58: Numero totale servizi | E58: S.6
C59: 2 | D59: 71 | E59: =C59/D59 -> 0.028169014
C61: Note:
C62: Si riferisce al questionario da riproporre 1 volta all'anno. Numero totale servizi = num. servizi totale ricavabile dall'elenco dei processi operativi
C65: Indicatore S.7 | D65: Livello di informatizzazione della struttura - Dotazioni PC, palmari, tablet
C66: Permette di fare una fotografia della corrente disponibilità di strumenti informatici dell'amministrazione locale, in particolare misura la disponibilità di PC, palmari, tablet.
C68: numero PC | D68: numero Tablet | E68: numero palmari | F68: numero dipendenti | G68: S.7
C69: 70 | D69: 0 | E69: 0 | F69: 60 | G69: =(C69+D69+E69)/F69 -> 1.1666667
C71: Note:
C72: Periodo di riferimento: un anno.
C75: Indicatore S.8 | D75: Livello di informatizzazione della struttura - Accessi ad internet
C76: Permette di fare una fotografia della corrente disponibilità di strumenti informatici dell'amministrazione locale, in particolare misura la disponibilità di postazioni con accesso ad internet.
C78: numero postazioni con accesso ad internet | D78: numero totale postazioni | E78: S.8
C79: 70 | D79: 70 | E79: =C79/D79 -> 1
C81: Note:
C82: Periodo di riferimento: un anno.
C85: Indicatore S.9 | D85: Tempo medio di risposta ai reclami
C86: Misura l'efficacia del processo di gestione dei reclami attraverso una valutazione della tempestività di risposta al cliente.
C88: ∑ gg (data chiusura reclamo - data ricezione reclamo) | D88: numero totale reclami | E88: S.9
C89: =25+16+10 -> 51 | D89: 3 | E89: =C89/D89 -> 17
C91: Note:
C92: Periodo di riferimento: un anno. Tempo medio misurato in giorni.
C95: Indicatore S.10 | D95: Livello di attivazione delle partnership
C96: Misura la propensione dell'amministrazione locale alla collaborazione con altre amministrazioni locali. Per partnership si intende un'alleanza strategica fra due o più organizzazioni che collaborano per conseguire un fine strategico comune che supera le possibilità delle singole amministrazioni.
C98: numero partnership attive | D98: numero abitanti | E98: S.10
C99: 2 | D99: =Governo!D45 -> 15520 | E99: =(C99/D99)*1000 -> 0.12886598
C101: Note:
C102: Si riferisce all'anno.
C105: Indicatore S.11 | D105: Qualità del sito web - Frequenza aggiornamento
C106: Indica l'impegno dell'amministrazione locale nel tenere informati i cittadini in tempo reale sia sui servizi offerti e le loro modalità di erogazione, sia su fatti, eventi e novità che riguardano l'amministrazione locale.
C108: Numero aggiornamentiti home page nel periodo | D108: numero gg (periodo di riferimento) | E108: S.11 - a
C109: 43 | D109: 30 | E109: =C109/D109 -> 1.4333333
C110: ∑ aggiornamenti pagine servizi in un anno | D110: numero pagine servizi | E110: S.11 - b
C111: 74 | D111: 82 | E111: =C111/D111 -> 0.90243902
C113: Note:
C114: Sciegliere il periodo di riferimento per gli aggiornamenti della home page (al mese o al giorno). Per le pagine dei servizi si riferisce all'anno.
C117: Indicatore S.12 | D117: Qualità del sito web - Accessibilità
C118: Misura la capacità dei sistemi informatici, nelle forme e nei limiti consentiti dalle conoscenze tecnologiche, di erogare servizi e fornire informazioni fruibili, senza discriminazioni, anche da parte di coloro che a causa di disabilità necessitano di tecnologie assistive o configurazioni particolari.
C120: Indicatore on/off
C121: NO
C123: Note:
C124: Si riferisce al momento della rilevazione. Indica la presenza o meno di tutti i seguenti elementi: Indica la presenza o meno nella home page del banner o del logo di accessibilità (o apposita sezione attestante l'accessibilità del sito)
C127: Indicatore S.13 | D127: Qualità del sito web - Usabilità
C128: Misura la capacità di un sistema di essere compreso, appreso, utilizzato e attraente per gli utenti quando usato sotto condizioni specificate. - La comprensibilità di un sito riguarda lo sforzo richiesto per capire il sistema - L'apprendibilità riguarda lo sforzo necessario all'utente per imparare ad usare il sistema - L'utilizzabilità si riferisce allo sforzo richiesto all'utente per utilizzare il sistema agendo sui suoi controlli.
C130: Indicatore on/off
C131: SI
C133: Note:
C134: Si riferisce al momento della rilevazione. Indica la presenza o meno di tutti i seguenti elementi: - note legali/credits - informazioni sulla privacy - indirizzo PEC dell'amministrazione - almeno un conttatto telefonico - chiarezza nel percorso delle sottopagine - albo on line - orari degli uffici - sezione trasparenza
C137: Indicatore S.14 | D137: Rispetto dei tempi di pagamento dei fornitori
C138: Indica la capacità dell'amministrazione locale a rispettare i tempi di pagamento.
C140: ∑ g (data pagamento fornitore - data pagamento concordato) | D140: numero fatture in scadenza nel periodo | E140: G.14
C141: 12 | D141: 8 | E141: =C141/D141 -> 1.5
C143: Note:
C144: Periodo di riferimento: 3 mesi. Tempo misurato in giorni. Potrebbe assumere valore positivo {significa ritardo medio nei pagamenti), ma anche valore negativo qualora le fatture fossero pagate in anticipo rispetto alla data concordata.
C147: Indicatore S.15 | D147: Copertura dei servizi con modalità on line
C148: Indica la capacità dell'amministrazione locale di adeguarsi alle nuove tecnologie e della sua volontà di rispondere in maniera sempre più efficiente alle esigenze dei cittadini.
C150: n° servizi erogabili on line fra gli 8 elencati | D150: S.15
C151: 1 | D151: =(C151/8) -> 0.125
C153: Note:
C154: Si riferisce al momento in cui viene fatta la rilevazione. I servizi erogabili on line sono: - certificati anagrafici, - pagamenti (contrawenzioni, mensa scolastica, luce votiva, tributi) - avanzamento pratiche, - Sistema Informativo Territoriale, - permessi accesso a ZTL.
C157: Indicatore S.16 | D157: Utilizzo servizi on line
C158: Indica la disponibilità/capacità dei cittadini di sfruttare le opportunità offerte dell'amministrazione locale.
C160: ∑ servizi erogati on line | D160: numero totale servizi | E160: numero tipologie servizi on line | F160: S.16
C161: 20 | D161: =D59 -> 71 | E161: 8 | F161: =(C161/D161)/E161 -> 0.035211268
C163: Note:
...

Sheet Totali
A2: N. | B2: Risultati
A3: G.1 | B3: =Governo!F7 -> 0.80856126
A4: G.2 | B4: =Governo!G17 -> 0.9
A5: G.3 | B5: =Governo!E28 -> >1 | C5: Tit. I | D5: ENTRATE
B6: =Governo!E29 -> <1 | C6: Tit. II
B7: =Governo!E30 -> >1 | C7: Tit. III
B8: =Governo!E31 -> =1 | C8: Tit. IV
B9: =Governo!E32 -> >1 | C9: Tit. V
B10: =Governo!E33 -> <1 | C10: Tit. I | D10: SPESA
B11: =Governo!E34 -> =1 | C11: Tit. II
B12: =Governo!E35 -> >1 | C12: Tit. III
A13: G.4 | B13: =Governo!E45 -> 126.28866
A14: G.5 | B14: =Governo!E55 -> 559.50782
A15: G.6 | B15: =Indicatore_on_off -> SI
A16: G.7 | B16: =Governo!C75 -> 5
A17: G.8 | B17: =Governo!D85 -> 0.66666667
A18: G.9 | B18: =Governo!E95 -> 0.5
A19: G.10 | B19: =Governo!E105 -> <1
A20: G.11 | B20: =Governo!E115 -> 0.25
A21: O.1 | B21: =Operativi!G7 -> 11.5
A22: O.2 | B22: =Operativi!G20 -> 3.6666667
A23: O.3 | B23: =Operativi!E32 -> 0.18518519
A24: O.4 | B24: =Operativi!E42 -> 0.8
A25: O.5 | B25: =Operativi!E52 -> 33.333333
A26: O.6 | B26: =Operativi!E62 -> 4
A27: O.7 | B27: =Operativi!F72 -> 0.9
A28: O.8 | B28: =Operativi!F82 -> 3
A29: O.9 | B29: =Operativi!E92 -> 0.9
A30: O.10 | B30: =Operativi!E102 -> 0.9375
A31: O.11 | B31: =Operativi!E112 -> 1
A32: O.12 | B32: =Operativi!E122 -> 3
A33: O.13 | B33: =Operativi!E132 -> 0.96069869
A34: O.14 | B34: =Operativi!E142 -> 0.00025773196
A35: O.15 | B35: =Operativi!E152 -> 0.00025773196
A36: O.16 | B36: =Operativi!E162 -> 0.51546392
A37: O.17 | B37: =Operativi!F172 -> 20.333333
A38: O.18 | B38: =Operativi!E182 -> 0.00096649485
A39: O.19 | B39: =Operativi!E192 -> 0.8
A40: O.20 | B40: =Operativi!E202 -> 0.75714286
A41: O.21 | B41: =Operativi!E212 -> 0.88
A42: O.22 | B42: =Operativi!E222 -> 0.1
A43: O.23 | B43: =Operativi!E232 -> F
A44: O.24 | B44: =Operativi!F246 -> >1
A45: O.25 | B45: vedi matrice
A46: S.1 | B46: =Supporto!G7 -> 11.427184
A47: S.2 | B47: =Supporto!F17 -> 1.5533981
A48: S.3 | B48: =Supporto!E29 -> 0.95398788
A49: S.4 | B49: =Supporto!E39 -> 0.8009594
A50: S.5 | B50: =Supporto!E49 -> 0.011019284
A51: S.6 | B51: =Supporto!E59 -> 0.028169014
A52: S.7 | B52: =Supporto!G69 -> 1.1666667
A53: S.8 | B53: =Supporto!E79 -> 1
A54: S.9 | B54: =Supporto!E89 -> 17
A55: S.10 | B55: =Supporto!E99 -> 0.12886598
A56: S.11 -a | B56: =Supporto!E109 -> 1.4333333
A57: S.11 -b | B57: =Supporto!E111 -> 0.90243902
A58: S.12 | B58: =Supporto!C121 -> NO
A59: S.13 | B59: =Supporto!C131 -> SI
A60: S.14 | B60: =Supporto!E141 -> 1.5
A61: S.15 | B61: =Supporto!D151 -> 0.125
A62: S.16 | B62: =Supporto!F161 -> 0.035211268
A63: S.17 | B63: =Supporto!E171 -> 0.35211268
A64: S.18 | B64: =Supporto!F183 -> 0.021759941
A65: S.19 | B65: =Supporto!F193 -> 0.7010582
A66: S.20 | B66: =Supporto!F203 -> 0.0079365079
A67: S.21 | B67: =Supporto!E213 -> 0.75
A68: S.22 | B68: =Supporto!F223 -> 8.5470085
A69: S.23 | B69: =Supporto!F233 -> 0.0026455026

Sheet   
B3: SI
B4: NO
